LICENSE
MANIFEST.in
README.md
setup.py
streamlit_chat_foto/__init__.py
streamlit_chat_foto.egg-info/PKG-INFO
streamlit_chat_foto.egg-info/SOURCES.txt
streamlit_chat_foto.egg-info/dependency_links.txt
streamlit_chat_foto.egg-info/requires.txt
streamlit_chat_foto.egg-info/top_level.txt
streamlit_chat_foto/frontend/build/asset-manifest.json
streamlit_chat_foto/frontend/build/bootstrap.min.css
streamlit_chat_foto/frontend/build/bootstrap.min.css.map
streamlit_chat_foto/frontend/build/index.html
streamlit_chat_foto/frontend/build/precache-manifest.b7f8306f2a03ca5a7e7f26b1609dc2aa.js
streamlit_chat_foto/frontend/build/service-worker.js
streamlit_chat_foto/frontend/build/static/js/2.01941a38.chunk.js
streamlit_chat_foto/frontend/build/static/js/2.01941a38.chunk.js.LICENSE.txt
streamlit_chat_foto/frontend/build/static/js/2.01941a38.chunk.js.map
streamlit_chat_foto/frontend/build/static/js/main.8d60b768.chunk.js
streamlit_chat_foto/frontend/build/static/js/main.8d60b768.chunk.js.map
streamlit_chat_foto/frontend/build/static/js/runtime-main.11ec9aca.js
streamlit_chat_foto/frontend/build/static/js/runtime-main.11ec9aca.js.map