Metadata-Version: 2.1
Name: streamlit-chat-foto
Version: 0.0.2.7
Summary: A streamlit component, to make chatbots
Home-page: https://github.com/Justin-KM/st-chat
Author: Yash Pravin Pawar, Yash Vardhan Kapil
Author-email: yashpawarp@gmail.com
Keywords: chat streamlit streamlit-component
Classifier: Programming Language :: Python :: 3
Classifier: Operating System :: OS Independent
Requires-Python: >=3.8
License-File: LICENSE
